rata/__init__.py
rata/__main__.py
rata/libs/__init__.py
rata/libs/application.py
rata/libs/edit_tasks.py
rata/libs/exceptions.py
rata/libs/io.py
rata/libs/tasks.py
rata/libs/widgets.py
rata_pkg_belugame-0.0.1.dist-info/LICENSE
rata_pkg_belugame-0.0.1.dist-info/METADATA
rata_pkg_belugame-0.0.1.dist-info/WHEEL
rata_pkg_belugame-0.0.1.dist-info/entry_points.txt
rata_pkg_belugame-0.0.1.dist-info/top_level.txt
rata_pkg_belugame-0.0.1.dist-info/RECORD
