Metadata-Version: 2.1
Name: rata-pkg-belugame
Version: 0.0.1
Summary: A CLI task time tracker loosely based on org-mode
Home-page: https://github.com/belugame/rata
Author: belugame
Author-email: mb@altmuehl.net
License: UNKNOWN
Platform: UNKNOWN
Classifier: Programming Language :: Python :: 3
Classifier: License :: OSI Approved :: MIT License
Classifier: Operating System :: OS Independent
Requires-Python: >=3.9
Requires-Dist: urwid
